pantools/VideoRecorder.py
pantools/__init__.py
pantools/face.py
pantools/logger.py
pantools/modules.rst
pantools/msg.py
pantools/net.py
pantools/send_recv.py
pantools-0.2.0.dist-info/WHEEL
pantools-0.2.0.dist-info/METADATA
pantools-0.2.0.dist-info/RECORD
